nsga2/__init__.py
nsga2/evolution.py
nsga2/individual.py
nsga2/population.py
nsga2/problem.py
nsga2/utils.py
nsga_2-1.2.0.dist-info/METADATA
nsga_2-1.2.0.dist-info/WHEEL
nsga_2-1.2.0.dist-info/top_level.txt
nsga_2-1.2.0.dist-info/RECORD
