Metadata-Version: 2.1
Name: nsga-2
Version: 1.2.0
Summary: A NSGA-II implementation
Home-page: https://github.com/baopng/NSGA-II
Author: Pham Ngo Gia Bao, Tram Loi Quan, Quan Thanh Tho, Akhil Garg
Author-email: ngogiabaopham@gmail.com
License: MIT
Keywords: nsga2 nsga ga multi-objective
Requires-Dist: tqdm
